pymarkets/__init__.py
pymarkets/asset.py
pymarkets/async_asset.py
pymarkets/price.py
pymarkets/price_history.py
pymarkets-0.0.1.dist-info/LICENSE
pymarkets-0.0.1.dist-info/METADATA
pymarkets-0.0.1.dist-info/WHEEL
pymarkets-0.0.1.dist-info/top_level.txt
pymarkets-0.0.1.dist-info/RECORD
