Metadata-Version: 2.1
Name: pymarkets
Version: 0.0.1
License-File: LICENSE
Requires-Dist: aiohttp
Requires-Dist: requests
